pretools/__init__.py
pretools/estimators.py
pretools/metrics.py
pretools/utils.py
pretools-0.3.0.dist-info/LICENSE
pretools-0.3.0.dist-info/METADATA
pretools-0.3.0.dist-info/WHEEL
pretools-0.3.0.dist-info/top_level.txt
pretools-0.3.0.dist-info/RECORD
