Metadata-Version: 2.1
Name: pretools
Version: 0.3.0
Summary: Preparation tools for machine learning
Home-page: UNKNOWN
Author: Kon
License: MIT License
Platform: UNKNOWN
Requires-Python: >=3.6
Requires-Dist: numpy
Requires-Dist: pandas
Requires-Dist: scikit-learn
Requires-Dist: tqdm
Provides-Extra: develop
Requires-Dist: catboost ; extra == 'develop'
